{"id":366,"fid":366,"name":"Find Leaves of Binary Tree","slug":"find-leaves-of-binary-tree","link":"https://leetcode.com/problems/find-leaves-of-binary-tree/description/","percent":62.729629422406234,"level":"Medium","category":"algorithms","totalAC":"33.6K","totalSubmit":"53.6K","desc":"Given a binary tree, collect a tree's nodes as if you were doing this: Collect and remove all leaves, repeat until the tree is empty.\r\n\r\n \r\n\r\nExample:\r\n\r\n\r\nInput: [1,2,3,4,5]\r\n  \r\n          1\r\n         / \\\r\n        2   3\r\n       / \\     \r\n      4   5    \r\n\r\nOutput: [[4,5,3],[2],[1]]\r\n\r\n\r\n \r\n\r\nExplanation:\r\n\r\n1. Removing the leaves [4,5,3] would result in this tree:\r\n\r\n\r\n          1\r\n         / \r\n        2          \r\n\r\n\r\n \r\n\r\n2. Now removing the leaf [2] would result in this tree:\r\n\r\n\r\n          1          \r\n\r\n\r\n \r\n\r\n3. Now removing the leaf [1] would result in the empty tree:\r\n\r\n\r\n          []         \r\n","templates":[{"value":"cpp","text":"C++","defaultCode":"/**\r\n * Definition for a binary tree node.\r\n * struct TreeNode {\r\n *     int val;\r\n *     TreeNode *left;\r\n *     TreeNode *right;\r\n *     TreeNode(int x) : val(x), left(NULL), right(NULL) {}\r\n * };\r\n */\r\nclass Solution {\r\npublic:\r\n    vector<vector<int>> findLeaves(TreeNode* root) {\r\n        \r\n    }\r\n};"},{"value":"java","text":"Java","defaultCode":"/**\r\n * Definition for a binary tree node.\r\n * public class TreeNode {\r\n *     int val;\r\n *     TreeNode left;\r\n *     TreeNode right;\r\n *     TreeNode(int x) { val = x; }\r\n * }\r\n */\r\nclass Solution {\r\n    public List<List<Integer>> findLeaves(TreeNode root) {\r\n        \r\n    }\r\n}"},{"value":"python","text":"Python","defaultCode":"# Definition for a binary tree node.\r\n# class TreeNode(object):\r\n#     def __init__(self, x):\r\n#         self.val = x\r\n#         self.left = None\r\n#         self.right = None\r\n\r\nclass Solution(object):\r\n    def findLeaves(self, root):\r\n        \"\"\"\r\n        :type root: TreeNode\r\n        :rtype: List[List[int]]\r\n        \"\"\""},{"value":"python3","text":"Python3","defaultCode":"# Definition for a binary tree node.\r\n# class TreeNode:\r\n#     def __init__(self, x):\r\n#         self.val = x\r\n#         self.left = None\r\n#         self.right = None\r\n\r\nclass Solution:\r\n    def findLeaves(self, root):\r\n        \"\"\"\r\n        :type root: TreeNode\r\n        :rtype: List[List[int]]\r\n        \"\"\""},{"value":"c","text":"C","defaultCode":"/**\r\n * Definition for a binary tree node.\r\n * struct TreeNode {\r\n *     int val;\r\n *     struct TreeNode *left;\r\n *     struct TreeNode *right;\r\n * };\r\n */\r\n/**\r\n * Return an array of arrays of size *returnSize.\r\n * The sizes of the arrays are returned as *columnSizes array.\r\n * Note: Both returned array and *columnSizes array must be malloced, assume caller calls free().\r\n */\r\nint** findLeaves(struct TreeNode* root, int** columnSizes, int* returnSize) {\r\n    \r\n}"},{"value":"csharp","text":"C#","defaultCode":"/**\r\n * Definition for a binary tree node.\r\n * public class TreeNode {\r\n *     public int val;\r\n *     public TreeNode left;\r\n *     public TreeNode right;\r\n *     public TreeNode(int x) { val = x; }\r\n * }\r\n */\r\npublic class Solution {\r\n    public IList<IList<int>> FindLeaves(TreeNode root) {\r\n        \r\n    }\r\n}"},{"value":"javascript","text":"JavaScript","defaultCode":"/**\r\n * Definition for a binary tree node.\r\n * function TreeNode(val) {\r\n *     this.val = val;\r\n *     this.left = this.right = null;\r\n * }\r\n */\r\n/**\r\n * @param {TreeNode} root\r\n * @return {number[][]}\r\n */\r\nvar findLeaves = function(root) {\r\n    \r\n};"},{"value":"ruby","text":"Ruby","defaultCode":"# Definition for a binary tree node.\r\n# class TreeNode\r\n#     attr_accessor :val, :left, :right\r\n#     def initialize(val)\r\n#         @val = val\r\n#         @left, @right = nil, nil\r\n#     end\r\n# end\r\n\r\n# @param {TreeNode} root\r\n# @return {Integer[][]}\r\ndef find_leaves(root)\r\n    \r\nend"},{"value":"swift","text":"Swift","defaultCode":"/**\n * Definition for a binary tree node.\n * public class TreeNode {\n *     public var val: Int\n *     public var left: TreeNode?\n *     public var right: TreeNode?\n *     public init(_ val: Int) {\n *         self.val = val\n *         self.left = nil\n *         self.right = nil\n *     }\n * }\n */\nclass Solution {\n    func findLeaves(_ root: TreeNode?) -> [[Int]] {\n\n    }\n}"},{"value":"golang","text":"Go","defaultCode":"/**\r\n * Definition for a binary tree node.\r\n * type TreeNode struct {\r\n *     Val int\r\n *     Left *TreeNode\r\n *     Right *TreeNode\r\n * }\r\n */\r\nfunc findLeaves(root *TreeNode) [][]int {\r\n    \r\n}"},{"value":"scala","text":"Scala","defaultCode":"/**\r\n * Definition for a binary tree node.\r\n * class TreeNode(var _value: Int) {\r\n *   var value: Int = _value\r\n *   var left: TreeNode = null\r\n *   var right: TreeNode = null\r\n * }\r\n */\r\nobject Solution {\r\n    def findLeaves(root: TreeNode): List[List[Int]] = {\r\n        \r\n    }\r\n}"},{"value":"kotlin","text":"Kotlin","defaultCode":"/**\r\n * Definition for a binary tree node.\r\n * class TreeNode(var `val`: Int = 0) {\r\n *     var left: TreeNode? = null\r\n *     var right: TreeNode? = null\r\n * }\r\n */\r\nclass Solution {\r\n    fun findLeaves(root: TreeNode?): List<List<Int>> {\r\n        \r\n    }\r\n}"}],"testcase":"[1,2,3,4,5]","testable":true,"templateMeta":{"name":"findLeaves","params":[{"name":"root","type":"TreeNode"}],"return":{"type":"list<list<integer>>","dealloc":true}}}